mcp_learning/__init__.py
mcp_learning/mcp_client/__init__.py
mcp_learning/mcp_client/client.py
mcp_learning/mcp_client/llm.py
mcp_learning/mcp_client/main.py
mcp_learning/mcp_client/orchestrator.py
mcp_learning/mcp_client/utils/__init__.py
mcp_learning/mcp_client/utils/configurations.py
mcp_learning/mcp_client/utils/console.py
mcp_learning/mcp_client/utils/dependencies.py
mcp_learning/mcp_client/utils/log.py
mcp_learning/mcp_client/utils/monitoring.py
mcp_learning/mcp_server/__init__.py
mcp_learning/mcp_server/arithmetic_operations/__init__.py
mcp_learning/mcp_server/arithmetic_operations/axioms/__init__.py
mcp_learning/mcp_server/arithmetic_operations/axioms/fundamental_operations.py
mcp_learning/mcp_server/arithmetic_operations/axioms/inverses.py
mcp_learning/mcp_server/arithmetic_operations/derived_operations.py
mcp_learning/mcp_server/configurations.py
mcp_learning/mcp_server/exponentiation.py
mcp_learning/mcp_server/main.py
mcp_learning/mcp_server/simplification.py
mcp_learning-0.2.0.dist-info/WHEEL
mcp_learning-0.2.0.dist-info/entry_points.txt
mcp_learning-0.2.0.dist-info/METADATA
mcp_learning-0.2.0.dist-info/RECORD
