Metadata-Version: 2.4
Name: mcp-learning
Version: 0.2.0
Summary: Exploring different features of MCP servers and clients
Keywords: mcp,mcp-server,mcp-client
Author: Anirban Ray
Author-email: Anirban Ray <39331844+yarnabrina@users.noreply.github.com>
License-Expression: AGPL-3.0-or-later
Classifier: Development Status :: 4 - Beta
Classifier: Framework :: Pydantic
Classifier: Framework :: Pydantic :: 2
Classifier: Intended Audience :: Developers
Classifier: Operating System :: OS Independent
Classifier: Programming Language :: Python
Classifier: Programming Language :: Python :: 3
Classifier: Programming Language :: Python :: 3 :: Only
Classifier: Programming Language :: Python :: 3.13
Classifier: Topic :: Software Development
Classifier: Topic :: Utilities
Classifier: Typing :: Typed
Requires-Dist: mcp>=1.21.0,<2
Requires-Dist: openai>=2.7.1,<3
Requires-Dist: pydantic>=2.12.4,<3
Requires-Dist: pydantic-settings>=2.11.0,<3
Requires-Dist: rich>=14.2.0,<15
Requires-Dist: prompt-toolkit>=3.0.52,<4 ; extra == 'cli'
Requires-Dist: langfuse>=3.9.1,<4 ; extra == 'monitoring'
Maintainer: Anirban Ray
Maintainer-email: Anirban Ray <39331844+yarnabrina@users.noreply.github.com>
Requires-Python: >=3.13, <3.14
Project-URL: documentation, https://yarnabrina.github.io/learn-model-context-protocol/
Project-URL: source, https://github.com/yarnabrina/learn-model-context-protocol
Provides-Extra: cli
Provides-Extra: monitoring
